appmake/__init__.py
appmake/coming_soon.py
appmake-0.0.1.dist-info/LICENSE.md
appmake-0.0.1.dist-info/METADATA
appmake-0.0.1.dist-info/WHEEL
appmake-0.0.1.dist-info/top_level.txt
appmake-0.0.1.dist-info/RECORD
